Workbook

Sheet Case
B2: Microsoft Excel Collegiate Challenge 2026
B4: Understanding Your FICO Credit Score - Junior Varsity Edition | M4: Case Author
M5: David Brown
M7: Case Design Team
M8: Eric Kelley
M9: Winston Smith
M10: Chris McNeil
M11: Gina Nicolosi
B14: Instructions
B15: Alex is a college senior who dreams of buying a new car after graduation.
B16: Before heading to the dealership, Alex wants to understand how a FICO credit score is calculated, and how a higher score means a lower interest rate and lower monthly payment on her car loan.
B17: Work through each level to help Alex understand her credit score and figure out how much car she can afford!
B20: Bonus Questions
B22: To make the game more exciting, we have created 5 bonus questions for you. These questions can be answered at any time during the game.
B24: Game # | C24: Relates to Level # | D24: Points | E24: Answer | G24: Question
B25: Bonus 1 | C25: 1 | D25: 30 | E25: =ROUND(SUM(G51:G70)/SUM(H51:H70)*100,0) -> 30 | G25: In Level 1,if one borrower had all of the games' balances and credit limits (excluding the example), what would be their total credit card utilization? Sum the balances and divide by the sum of the credit limits and round to the nearest integer. Percents should be expressed as whole numbers, i.e., answer 24% as 24.
B26: Bonus 2 | C26: 3 | D26: 40 | E26: =COUNTIF(N129:R148,">50") -> 24 | G26: In Level 3, how many individual credit cards across all 20 games (excluding the example) have a utilization rate greater than 50%?
B27: Bonus 3 | C27: 5 | D27: 50 | E27: 715 | G27: In Level 5, what is the median FICO score across all 21 games (include the example)?
B28: Bonus 4 | C28: 6 | D28: 60 | E28: 207 | G28: In Level 6, what is the total number of FICO points lost to the previous credit inquiries across all 20 games combined (excluding the example)?
B29: Bonus 5 | C29: 7 | D29: 70 | E29: =SUMIF(H306:H325,">=700",_xlfn.ANCHORARRAY(E306))-SUMIF(H306:H325,"<700",_xlfn.ANCHORARRAY(E306)) -> 153848 | G29: In Level 7, how much more can borrowers with FICO scores of 700 or higher afford versus those with lower FICO scores? Sum the answers for the high FICO scores (>=700) and subtract the sum of the answers for the low FICO scores (<700).
B31: Questions
B33: Level 1 | C33: Easy
B35: After graduation, Alex wants to buy a car and needs a great credit score to get a low interest rate.
B36: One key factor is Credit Utilization — the percentage of a credit limit that is currently being used.
B37: Calculate Credit Utilization (=balance/limit) for each game based on the given balances and credit limits.
B38: Express Credit Utilization as a percentage by multiplying the calculation by 100.
B40: Example1: A card with a $350 balance and a $1,000 limit has a utilization rate of 35%. 35% x 100 = 35.
B42: Answer Hints:
B43: Game 1's answer is between 20 and 24.
B44: Game 2's answer is between 30 and 34.
B45: Game 3's answer is between 6 and 10.
B47: Game # | C47: Level | D47: Points | E47: Answer | G47: Balance ($) | H47: Credit Limit ($)
B49: Example1 | C49: 1 | D49: 0 | E49: 35 | G49: 350 | H49: 1000
B51: 1 | C51: 1 | D51: 4 | E51: =(G51/H51)*100 -> 22 | G51: 220 | H51: 1000
B52: 2 | C52: 1 | D52: 4 | E52: =(G52/H52)*100 -> 32 | G52: 480 | H52: 1500
B53: 3 | C53: 1 | D53: 4 | E53: =(G53/H53)*100 -> 8 | G53: 160 | H53: 2000
B54: 4 | C54: 1 | D54: 4 | E54: =(G54/H54)*100 -> 33 | G54: 825 | H54: 2500
B55: 5 | C55: 1 | D55: 4 | E55: =(G55/H55)*100 -> 35 | G55: 630 | H55: 1800
B56: 6 | C56: 1 | D56: 4 | E56: =(G56/H56)*100 -> 19 | G56: 95 | H56: 500
B57: 7 | C57: 1 | D57: 4 | E57: =(G57/H57)*100 -> 30 | G57: 1200 | H57: 4000
B58: 8 | C58: 1 | D58: 4 | E58: =(G58/H58)*100 -> 48 | G58: 360 | H58: 750
B59: 9 | C59: 1 | D59: 4 | E59: =(G59/H59)*100 -> 18 | G59: 540 | H59: 3000
B60: 10 | C60: 1 | D60: 4 | E60: =(G60/H60)*100 -> 42 | G60: 2100 | H60: 5000
B61: 11 | C61: 1 | D61: 4 | E61: =(G61/H61)*100 -> 22 | G61: 88 | H61: 400
B62: 12 | C62: 1 | D62: 4 | E62: =(G62/H62)*100 -> 45 | G62: 900 | H62: 2000
... B70: 20 | C70: 1 | D70: 4 | E70: =(G70/H70)*100 -> 30 | G70: 990 | H70: 3300
B72: FICO Tip: Keep credit utilization as low as possible.
B74: Level 2 | C74: Easy
B76: Alex discovers that Amounts Owed — the total balance across all credit cards — also affects the credit score.
B77: The lower the total balance, the better! Calculate the total balance across all of Alex's credit cards.
B79: Example2: Cards with balances of $210, $85, and $540 have a total owed of $835.
B81: Answer Hints:
B82: Game 21's answer is between 1,045 and 1,053.
B83: Game 22's answer is between 2,575 and 2,584.
B84: Game 23's answer is between 784 and 793.
B86: Game # | C86: Level | D86: Points | E86: Answer | G86: Card 1 Balance | H86: Card 2 Balance | I86: Card 3 Balance | J86: Card 4 Balance | K86: Card 5 Balance | L86: Card 6 Balance
B88: Example2 | C88: 2 | D88: 0 | E88: 835 | G88: 210 | H88: 85 | I88: 540
B90: 21 | C90: 2 | D90: 6 | E90: =SUM(G90:L90) -> 1050 | G90: 450 | H90: 320 | I90: 280
B91: 22 | C91: 2 | D91: 6 | E91: =SUM(G91:L91) -> 2580 | G91: 880 | H91: 650 | I91: 710 | J91: 340
B92: 23 | C92: 2 | D92: 6 | E92: =SUM(G92:L92) -> 790 | G92: 195 | H92: 410 | I92: 185
B93: 24 | C93: 2 | D93: 6 | E93: =SUM(G93:L93) -> 3475 | G93: 1200 | H93: 880 | I93: 630 | J93: 475 | K93: 290
B94: 25 | C94: 2 | D94: 6 | E94: =SUM(G94:L94) -> 790 | G94: 560 | H94: 230
B95: 26 | C95: 2 | D95: 6 | E95: =SUM(G95:L95) -> 1310 | G95: 340 | H95: 120 | I95: 580 | J95: 270
B96: 27 | C96: 2 | D96: 6 | E96: =SUM(G96:L96) -> 5970 | G96: 2100 | H96: 1500 | I96: 980 | J96: 670 | K96: 430 | L96: 290
B97: 28 | C97: 2 | D97: 6 | E97: =SUM(G97:L97) -> 285 | G97: 75 | H97: 210
B98: 29 | C98: 2 | D98: 6 | E98: =SUM(G98:L98) -> 1730 | G98: 490 | H98: 310 | I98: 750 | J98: 180
B99: 30 | C99: 2 | D99: 6 | E99: =SUM(G99:L99) -> 1850 | G99: 920 | H99: 650 | I99: 280
B100: 31 | C100: 2 | D100: 6 | E100: =SUM(G100:L100) -> 4680 | G100: 1800 | H100: 1200 | I100: 760 | J100: 540 | K100: 380
B101: 32 | C101: 2 | D101: 6 | E101: =SUM(G101:L101) -> 225 | G101: 130 | H101: 95
B102: 33 | C102: 2 | D102: 6 | E102: =SUM(G102:L102) -> 2230 | G102: 680 | H102: 450 | I102: 290 | J102: 810
B103: 34 | C103: 2 | D103: 6 | E103: =SUM(G103:L103) -> 1145 | G103: 350 | H103: 175 | I103: 620
B104: 35 | C104: 2 | D104: 6 | E104: =SUM(G104:L104) -> 7050 | G104: 2400 | H104: 1800 | I104: 1100 | J104: 750 | K104: 600 | L104: 400
B105: 36 | C105: 2 | D105: 6 | E105: =SUM(G105:L105) -> 630 | G105: 440 | H105: 190
B106: 37 | C106: 2 | D106: 6 | E106: =SUM(G106:L106) -> 1900 | G106: 760 | H106: 520 | I106: 380 | J106: 240
B107: 38 | C107: 2 | D107: 6 | E107: =SUM(G107:L107) -> 590 | G107: 85 | H107: 310 | I107: 195
B108: 39 | C108: 2 | D108: 6 | E108: =SUM(G108:L108) -> 4260 | G108: 1500 | H108: 1100 | I108: 820 | J108: 530 | K108: 310
B109: 40 | C109: 2 | D109: 6 | E109: =SUM(G109:L109) -> 1400 | G109: 580 | H109: 390 | I109: 260 | J109: 170
B111: FICO Tip: Keeping current on multiple accounts can improve your credit score.
B113: Level 3 | C113: Medium
B115: Alex learns that lenders often look at the WORST card — the one with the highest utilization rate.
B116: Calculate the highest utilization rate across all of Alex's credit cards.
B118: Example3: The three cards have utilizations (balance/limit) of 45%, 22%, and 68%, so the highest utilization is 68%.
B120: Answer Hints:
B121: Game 41's answer is between 74 and 81.
B122: Game 42's answer is between 77 and 84.
B123: Game 43's answer is between 73 and 80.
B125: Game # | C125: Level | D125: Points | E125: Answer | G125: Card 1 Balance | H125: Card 1 Limit | I125: Card 2 Balance | J125: Card 2 Limit | K125: Card 3 Balance | L125: Card 3 Limit
B127: Example3 | C127: 3 | D127: 0 | E127: 68 | G127: 450 | H127: 1000 | I127: 220 | J127: 1000 | K127: 680 | L127: 1000
B129: 41 | C129: 3 | D129: 7 | E129: =MAX(N129,P129,R129) -> 78 | G129: 528 | H129: 1200 | I129: 660 | J129: 1000 | K129: 1950 | L129: 2500 | N129: =(G129/H129)*100 -> 44 | P129: =(I129/J129)*100 -> 66 | R129: =(K129/L129)*100 -> 78
B130: 42 | C130: 3 | D130: 7 | E130: =MAX(N130,P130,R130) -> 80 | G130: 2240 | H130: 2800 | I130: 144 | J130: 900 | K130: 360 | L130: 1800 | N130: =(G130/H130)*100 -> 80 | P130: =(I130/J130)*100 -> 16 | R130: =(K130/L130)*100 -> 20
B131: 43 | C131: 3 | D131: 7 | E131: =MAX(N131,P131,R131) -> 77 | G131: 616 | H131: 800 | I131: 640 | J131: 2000 | K131: 140 | L131: 1000 | N131: =(G131/H131)*100 -> 77 | P131: =(I131/J131)*100 -> 32 | R131: =(K131/L131)*100 -> 14
B132: 44 | C132: 3 | D132: 7 | E132: =MAX(N132,P132,R132) -> 65 | G132: 65 | H132: 500 | I132: 615 | J132: 1500 | K132: 1820 | L132: 2800 | N132: =(G132/H132)*100 -> 13 | P132: =(I132/J132)*100 -> 41 | R132: =(K132/L132)*100 -> 65
B133: 45 | C133: 3 | D133: 7 | E133: =MAX(N133,P133,R133) -> 69 | G133: 780 | H133: 3000 | I133: 414 | J133: 600 | K133: 377 | L133: 1300 | N133: =(G133/H133)*100 -> 26 | P133: =(I133/J133)*100 -> 69 | R133: =(K133/L133)*100 -> 29
B134: 46 | C134: 3 | D134: 7 | E134: =MAX(N134,P134,R134) -> 61 | G134: 210 | H134: 1000 | I134: 340 | J134: 2000 | K134: 915 | L134: 1500 | N134: =(G134/H134)*100 -> 21 | P134: =(I134/J134)*100 -> 17 | R134: =(K134/L134)*100 -> 61
B135: 47 | C135: 3 | D135: 7 | E135: =MAX(N135,P135,R135) -> 52 | G135: 52 | H135: 400 | I135: 288 | J135: 1200 | K135: 1560 | L135: 3000 | N135: =(G135/H135)*100 -> 13 | P135: =(I135/J135)*100 -> 24 | R135: =(K135/L135)*100 -> 52
B136: 48 | C136: 3 | D136: 7 | E136: =MAX(N136,P136,R136) -> 58 | G136: 400 | H136: 4000 | I136: 145 | J136: 500 | K136: 1740 | L136: 3000 | N136: =(G136/H136)*100 -> 10 | P136: =(I136/J136)*100 -> 29 | R136: =(K136/L136)*100 -> 58
B137: 49 | C137: 3 | D137: 7 | E137: =MAX(N137,P137,R137) -> 54 | G137: 90 | H137: 300 | I137: 200 | J137: 2000 | K137: 540 | L137: 1000 | N137: =(G137/H137)*100 -> 30 | P137: =(I137/J137)*100 -> 10 | R137: =(K137/L137)*100 -> 54
B138: 50 | C138: 3 | D138: 7 | E138: =MAX(N138,P138,R138) -> 79 | G138: 1150 | H138: 5000 | I138: 632 | J138: 800 | K138: 1316 | L138: 2800 | N138: =(G138/H138)*100 -> 23 | P138: =(I138/J138)*100 -> 79 | R138: =(K138/L138)*100 -> 47
B139: 51 | C139: 3 | D139: 7 | E139: =MAX(N139,P139,R139) -> 50 | G139: 750 | H139: 1500 | I139: 525 | J139: 2500 | K139: 350 | L139: 700 | N139: =(G139/H139)*100 -> 50 | P139: =(I139/J139)*100 -> 21 | R139: =(K139/L139)*100 -> 50
B140: 52 | C140: 3 | D140: 7 | E140: =MAX(N140,P140,R140) -> 69 | G140: 116 | H140: 200 | I140: 1188 | J140: 1800 | K140: 828 | L140: 1200 | N140: =(G140/H140)*100 -> 58 | P140: =(I140/J140)*100 -> 66 | R140: =(K140/L140)*100 -> 69
...

Sheet Graded Answers
B1: Your Answers
B2: Game # | C2: Answer | D2: Points
B3: Bonus 1 | C3: =IF(ISBLANK(Case!E25), "", Case!E25) -> 30 | D3: 30
B4: Bonus 2 | C4: =IF(ISBLANK(Case!E26), "", Case!E26) -> 24 | D4: 40
B5: Bonus 3 | C5: =IF(ISBLANK(Case!E27), "", Case!E27) -> 715 | D5: 50
B6: Bonus 4 | C6: =IF(ISBLANK(Case!E28), "", Case!E28) -> 207 | D6: 60
B7: Bonus 5 | C7: =IF(ISBLANK(Case!E29), "", Case!E29) -> 153848 | D7: 70
B8: 1 | C8: =IF(ISBLANK(Case!E51), "", Case!E51) -> 22 | D8: 4
B9: =B8+1 -> 2 | C9: =IF(ISBLANK(Case!E52), "", Case!E52) -> 32 | D9: 4
B10: =B9+1 -> 3 | C10: =IF(ISBLANK(Case!E53), "", Case!E53) -> 8 | D10: 4
B11: =B10+1 -> 4 | C11: =IF(ISBLANK(Case!E54), "", Case!E54) -> 33 | D11: 4
B12: =B11+1 -> 5 | C12: =IF(ISBLANK(Case!E55), "", Case!E55) -> 35 | D12: 4
B13: =B12+1 -> 6 | C13: =IF(ISBLANK(Case!E56), "", Case!E56) -> 19 | D13: 4
B14: =B13+1 -> 7 | C14: =IF(ISBLANK(Case!E57), "", Case!E57) -> 30 | D14: 4
B15: =B14+1 -> 8 | C15: =IF(ISBLANK(Case!E58), "", Case!E58) -> 48 | D15: 4
B16: =B15+1 -> 9 | C16: =IF(ISBLANK(Case!E59), "", Case!E59) -> 18 | D16: 4
B17: =B16+1 -> 10 | C17: =IF(ISBLANK(Case!E60), "", Case!E60) -> 42 | D17: 4
B18: =B17+1 -> 11 | C18: =IF(ISBLANK(Case!E61), "", Case!E61) -> 22 | D18: 4
B19: =B18+1 -> 12 | C19: =IF(ISBLANK(Case!E62), "", Case!E62) -> 45 | D19: 4
B20: =B19+1 -> 13 | C20: =IF(ISBLANK(Case!E63), "", Case!E63) -> 39 | D20: 4
... B27: =B26+1 -> 20 | C27: =IF(ISBLANK(Case!E70), "", Case!E70) -> 30 | D27: 4
B28: =B27+1 -> 21 | C28: =IF(ISBLANK(Case!E90), "", Case!E90) -> 1050 | D28: 6
B29: =B28+1 -> 22 | C29: =IF(ISBLANK(Case!E91), "", Case!E91) -> 2580 | D29: 6
B30: =B29+1 -> 23 | C30: =IF(ISBLANK(Case!E92), "", Case!E92) -> 790 | D30: 6
B31: =B30+1 -> 24 | C31: =IF(ISBLANK(Case!E93), "", Case!E93) -> 3475 | D31: 6
B32: =B31+1 -> 25 | C32: =IF(ISBLANK(Case!E94), "", Case!E94) -> 790 | D32: 6
B33: =B32+1 -> 26 | C33: =IF(ISBLANK(Case!E95), "", Case!E95) -> 1310 | D33: 6
B34: =B33+1 -> 27 | C34: =IF(ISBLANK(Case!E96), "", Case!E96) -> 5970 | D34: 6
B35: =B34+1 -> 28 | C35: =IF(ISBLANK(Case!E97), "", Case!E97) -> 285 | D35: 6
B36: =B35+1 -> 29 | C36: =IF(ISBLANK(Case!E98), "", Case!E98) -> 1730 | D36: 6
B37: =B36+1 -> 30 | C37: =IF(ISBLANK(Case!E99), "", Case!E99) -> 1850 | D37: 6
B38: =B37+1 -> 31 | C38: =IF(ISBLANK(Case!E100), "", Case!E100) -> 4680 | D38: 6
B39: =B38+1 -> 32 | C39: =IF(ISBLANK(Case!E101), "", Case!E101) -> 225 | D39: 6
... B47: =B46+1 -> 40 | C47: =IF(ISBLANK(Case!E109), "", Case!E109) -> 1400 | D47: 6
B48: =B47+1 -> 41 | C48: =IF(ISBLANK(Case!E129), "", Case!E129) -> 78 | D48: 7
B49: =B48+1 -> 42 | C49: =IF(ISBLANK(Case!E130), "", Case!E130) -> 80 | D49: 7
B50: =B49+1 -> 43 | C50: =IF(ISBLANK(Case!E131), "", Case!E131) -> 77 | D50: 7
B51: =B50+1 -> 44 | C51: =IF(ISBLANK(Case!E132), "", Case!E132) -> 65 | D51: 7
B52: =B51+1 -> 45 | C52: =IF(ISBLANK(Case!E133), "", Case!E133) -> 69 | D52: 7
B53: =B52+1 -> 46 | C53: =IF(ISBLANK(Case!E134), "", Case!E134) -> 61 | D53: 7
B54: =B53+1 -> 47 | C54: =IF(ISBLANK(Case!E135), "", Case!E135) -> 52 | D54: 7
B55: =B54+1 -> 48 | C55: =IF(ISBLANK(Case!E136), "", Case!E136) -> 58 | D55: 7
B56: =B55+1 -> 49 | C56: =IF(ISBLANK(Case!E137), "", Case!E137) -> 54 | D56: 7
B57: =B56+1 -> 50 | C57: =IF(ISBLANK(Case!E138), "", Case!E138) -> 79 | D57: 7
B58: =B57+1 -> 51 | C58: =IF(ISBLANK(Case!E139), "", Case!E139) -> 50 | D58: 7
B59: =B58+1 -> 52 | C59: =IF(ISBLANK(Case!E140), "", Case!E140) -> 69 | D59: 7
... B67: =B66+1 -> 60 | C67: =IF(ISBLANK(Case!E148), "", Case!E148) -> 67 | D67: 7
B68: =B67+1 -> 61 | C68: =IF(ISBLANK(Case!E169), "", Case!E169) -> 2 | D68: 7
B69: =B68+1 -> 62 | C69: =IF(ISBLANK(Case!E170), "", Case!E170) -> 3 | D69: 7
B70: =B69+1 -> 63 | C70: =IF(ISBLANK(Case!E171), "", Case!E171) -> 4 | D70: 7
B71: =B70+1 -> 64 | C71: =IF(ISBLANK(Case!E172), "", Case!E172) -> 4 | D71: 7
B72: =B71+1 -> 65 | C72: =IF(ISBLANK(Case!E173), "", Case!E173) -> 3 | D72: 7
B73: =B72+1 -> 66 | C73: =IF(ISBLANK(Case!E174), "", Case!E174) -> 4 | D73: 7
B74: =B73+1 -> 67 | C74: =IF(ISBLANK(Case!E175), "", Case!E175) -> 2 | D74: 7
B75: =B74+1 -> 68 | C75: =IF(ISBLANK(Case!E176), "", Case!E176) -> 5 | D75: 7
B76: =B75+1 -> 69 | C76: =IF(ISBLANK(Case!E177), "", Case!E177) -> 4 | D76: 7
B77: =B76+1 -> 70 | C77: =IF(ISBLANK(Case!E178), "", Case!E178) -> 2 | D77: 7
B78: =B77+1 -> 71 | C78: =IF(ISBLANK(Case!E179), "", Case!E179) -> 3 | D78: 7
B79: =B78+1 -> 72 | C79: =IF(ISBLANK(Case!E180), "", Case!E180) -> 4 | D79: 7
... B87: =B86+1 -> 80 | C87: =IF(ISBLANK(Case!E188), "", Case!E188) -> 4 | D87: 7
B88: =B87+1 -> 81 | C88: =IF(ISBLANK(Case!E216), "", Case!E216) -> 711 | D88: 8
B89: =B88+1 -> 82 | C89: =IF(ISBLANK(Case!E217), "", Case!E217) -> 669 | D89: 8
B90: =B89+1 -> 83 | C90: =IF(ISBLANK(Case!E218), "", Case!E218) -> 768 | D90: 8
B91: =B90+1 -> 84 | C91: =IF(ISBLANK(Case!E219), "", Case!E219) -> 787 | D91: 8
B92: =B91+1 -> 85 | C92: =IF(ISBLANK(Case!E220), "", Case!E220) -> 614 | D92: 8
B93: =B92+1 -> 86 | C93: =IF(ISBLANK(Case!E221), "", Case!E221) -> 696 | D93: 8
B94: =B93+1 -> 87 | C94: =IF(ISBLANK(Case!E222), "", Case!E222) -> 807 | D94: 8
B95: =B94+1 -> 88 | C95: =IF(ISBLANK(Case!E223), "", Case!E223) -> 654 | D95: 8
B96: =B95+1 -> 89 | C96: =IF(ISBLANK(Case!E224), "", Case!E224) -> 736 | D96: 8
B97: =B96+1 -> 90 | C97: =IF(ISBLANK(Case!E225), "", Case!E225) -> 586 | D97: 8
B98: =B97+1 -> 91 | C98: =IF(ISBLANK(Case!E226), "", Case!E226) -> 763 | D98: 8
B99: =B98+1 -> 92 | C99: =IF(ISBLANK(Case!E227), "", Case!E227) -> 682 | D99: 8
... B107: =B106+1 -> 100 | C107: =IF(ISBLANK(Case!E235), "", Case!E235) -> 743 | D107: 8
B108: =B107+1 -> 101 | C108: =IF(ISBLANK(Case!E261), "", Case!E261) -> 737 | D108: 8
B109: =B108+1 -> 102 | C109: =IF(ISBLANK(Case!E262), "", Case!E262) -> 739 | D109: 8
B110: =B109+1 -> 103 | C110: =IF(ISBLANK(Case!E263), "", Case!E263) -> 758 | D110: 8
B111: =B110+1 -> 104 | C111: =IF(ISBLANK(Case!E264), "", Case!E264) -> 779 | D111: 8
B112: =B111+1 -> 105 | C112: =IF(ISBLANK(Case!E265), "", Case!E265) -> 698 | D112: 8
B113: =B112+1 -> 106 | C113: =IF(ISBLANK(Case!E266), "", Case!E266) -> 717 | D113: 8
B114: =B113+1 -> 107 | C114: =IF(ISBLANK(Case!E267), "", Case!E267) -> 797 | D114: 8
B115: =B114+1 -> 108 | C115: =IF(ISBLANK(Case!E268), "", Case!E268) -> 679 | D115: 8
B116: =B115+1 -> 109 | C116: =IF(ISBLANK(Case!E269), "", Case!E269) -> 747 | D116: 8
B117: =B116+1 -> 110 | C117: =IF(ISBLANK(Case!E270), "", Case!E270) -> 659 | D117: 8
B118: =B117+1 -> 111 | C118: =IF(ISBLANK(Case!E271), "", Case!E271) -> 808 | D118: 8
B119: =B118+1 -> 112 | C119: =IF(ISBLANK(Case!E272), "", Case!E272) -> 729 | D119: 8
... B127: =B126+1 -> 120 | C127: =IF(ISBLANK(Case!E280), "", Case!E280) -> 739 | D127: 8
B128: =B127+1 -> 121 | C128: =IF(ISBLANK(Case!E306), "", Case!E306) -> 19960 | D128: 10
B129: =B128+1 -> 122 | C129: =IF(ISBLANK(Case!E307), "", Case!E307) -> 16099 | D129: 10
B130: =B129+1 -> 123 | C130: =IF(ISBLANK(Case!E308), "", Case!E308) -> 26178 | D130: 10
B131: =B130+1 -> 124 | C131: =IF(ISBLANK(Case!E309), "", Case!E309) -> 32189 | D131: 10
B132: =B131+1 -> 125 | C132: =IF(ISBLANK(Case!E310), "", Case!E310) -> 12892 | D132: 10
B133: =B132+1 -> 126 | C133: =IF(ISBLANK(Case!E311), "", Case!E311) -> 21676 | D133: 10
B134: =B133+1 -> 127 | C134: =IF(ISBLANK(Case!E312), "", Case!E312) -> 28104 | D134: 10
B135: =B134+1 -> 128 | C135: =IF(ISBLANK(Case!E313), "", Case!E313) -> 17479 | D135: 10
B136: =B135+1 -> 129 | C136: =IF(ISBLANK(Case!E314), "", Case!E314) -> 23703 | D136: 10
B137: =B136+1 -> 130 | C137: =IF(ISBLANK(Case!E315), "", Case!E315) -> 34871 | D137: 10
B138: =B137+1 -> 131 | C138: =IF(ISBLANK(Case!E316), "", Case!E316) -> 13752 | D138: 10
B139: =B138+1 -> 132 | C139: =IF(ISBLANK(Case!E317), "", Case!E317) -> 20231 | D139: 10
... B147: =B146+1 -> 140 | C147: =IF(ISBLANK(Case!E325), "", Case!E325) -> 22158 | D147: 10
D148: =SUM(D3:D147) -> 1250 | J148: =D148*0.78 -> 975
...
